mirror_dedupe/__init__.py
mirror_dedupe/cli.py
mirror_dedupe/config.py
mirror_dedupe/dedupe.py
mirror_dedupe/download.py
mirror_dedupe/indices.py
mirror_dedupe/orchestrate.py
mirror_dedupe/scan.py
mirror_dedupe/sync.py
mirror_dedupe/utils.py
mirror_dedupe-0.2.10.dist-info/METADATA
mirror_dedupe-0.2.10.dist-info/WHEEL
mirror_dedupe-0.2.10.dist-info/entry_points.txt
mirror_dedupe-0.2.10.dist-info/top_level.txt
mirror_dedupe-0.2.10.dist-info/RECORD
