Metadata-Version: 2.4
Name: mirror-dedupe
Version: 0.2.10
Summary: Ubuntu mirror synchronisation with global deduplication
Home-page: https://github.com/munger/mirror-dedupe
Author: Tim Hosking
Author-email: Tim Hosking <tim@mungerware.com>
License: MIT
Project-URL: Homepage, https://github.com/munger/mirror-dedupe
Project-URL: Bug Tracker, https://github.com/munger/mirror-dedupe/issues
Project-URL: Source Code, https://github.com/munger/mirror-dedupe
Keywords: mirror,deduplication,hardlink,ubuntu,repository,apt
Classifier: Development Status :: 4 - Beta
Classifier: Environment :: Console
Classifier: Intended Audience :: System Administrators
Classifier: License :: OSI Approved :: MIT License
Classifier: Operating System :: POSIX :: Linux
Classifier: Programming Language :: Python :: 3
Classifier: Programming Language :: Python :: 3.8
Classifier: Programming Language :: Python :: 3.9
Classifier: Programming Language :: Python :: 3.10
Classifier: Programming Language :: Python :: 3.11
Classifier: Programming Language :: Python :: 3.12
Classifier: Topic :: System :: Archiving :: Mirroring
Classifier: Topic :: System :: Systems Administration
Requires-Python: >=3.8
Requires-Dist: PyYAML>=6.0
Dynamic: author
Dynamic: home-page
Dynamic: requires-python
